anas/__init__.py
anas-0.0.0.1.data/scripts/anas
anas-0.0.0.1.dist-info/METADATA
anas-0.0.0.1.dist-info/WHEEL
anas-0.0.0.1.dist-info/top_level.txt
anas-0.0.0.1.dist-info/RECORD
